text2structured/__init__.py
text2structured/main.py
text2structured/prompts.py
text2structured-2025.12.20175536.dist-info/METADATA
text2structured-2025.12.20175536.dist-info/WHEEL
text2structured-2025.12.20175536.dist-info/top_level.txt
text2structured-2025.12.20175536.dist-info/RECORD
