Metadata-Version: 2.4
Name: text2structured
Version: 2025.12.20175536
Summary: A new package designed to transform unstructured text inputs into structured, actionable insights using advanced language models. This package leverages the capabilities of llmatch-messages to ensure 
Author-email: text2structured <hi@eugene.plus>
License: MIT
Project-URL: Homepage, https://github.com/chigwell/text2structured
Requires-Python: >=3.9
Requires-Dist: langchain-llm7>=0.0.0
Requires-Dist: llmatch-messages>=0.0.0
Requires-Dist: langchain-core>=0.3.0
